{"cameraMode":{"drawMode":0,"name":"Shaded","section":"Shading Mode"},"sceneLighting":true,"audioPlay":false,"sceneViewState":{"m_AlwaysRefresh":false,"showFog":true,"showSkybox":true,"showFlares":true,"showImageEffects":true,"showParticleSystems":true,"showVisualEffectGraphs":true,"m_FxEnabled":false},"in2DMode":false,"pivot":{"x":3.2915854454040529,"y":0.68853759765625,"z":4.45848274230957},"rotation":{"x":0.6444324851036072,"y":0.1604546308517456,"z":-0.1408117264509201,"w":0.7342954277992249},"size":5.366025924682617,"orthographic":false}